markdown_img/__init__.py
markdown_img/__main__.py
markdown_img/config.py
markdown_img/config_backup.py
markdown_img/download_help.py
markdown_img/globalization.py
markdown_img/help.info
markdown_img/help_en.info
markdown_img/img_service_manager.py
markdown_img/main.py
markdown_img/qcloud_client.py
markdown_img/qiniu_client.py
markdown_img/smms_img.py
markdown_img/time_helper.py
markdown_img/user_exception.py
markdown_img/compress/__init__.py
markdown_img/compress/compress.py
markdown_img/compress/compress_manager.py
markdown_img/compress/compress_service.py
markdown_img/compress/none_compress_service.py
markdown_img/compress/pillow_compress_service.py
markdown_img/compress/tinypng_compress_service.py
markdown_img/img_service/Upyun_img_service.py
markdown_img/img_service/__init__.py
markdown_img/img_service/bilibili_img_service.py
markdown_img/img_service/fz_img_service.py
markdown_img/img_service/img_service.py
markdown_img/img_service/none_img_service.py
markdown_img/img_service/qcloud_img_service.py
markdown_img/img_service/qiniu_img_service.py
markdown_img/img_service/smms_img_service.py
markdown_img/img_service/vimcn_img_service.py
markdown_img/img_service/yujian_img_service.py
markdown_img/tools/__init__.py
markdown_img/tools/debug.py
markdown_img/tools/file_tools.py
markdown_img/tools/my_time.py
markdown_img_icexmoon-1.0.0.dist-info/licenses/LICENSE
markdown_img_icexmoon-1.0.0.dist-info/METADATA
markdown_img_icexmoon-1.0.0.dist-info/WHEEL
markdown_img_icexmoon-1.0.0.dist-info/entry_points.txt
markdown_img_icexmoon-1.0.0.dist-info/top_level.txt
markdown_img_icexmoon-1.0.0.dist-info/RECORD
