Metadata-Version: 2.4
Name: markdown-img-icexmoon
Version: 1.0.0
Summary: A program for find and upload images in markdown file and will replace them.
Home-page: https://github.com/icexmoon/markdown-img
Author: icexmoon
Author-email: icexmoon@qq.com
Project-URL: Bug Tracker, https://github.com/icexmoon/markdown-img/issues
Classifier: Programming Language :: Python :: 3
Classifier: License :: OSI Approved :: MIT License
Classifier: Operating System :: OS Independent
Requires-Python: >=3.6
License-File: LICENSE
Requires-Dist: requests
Requires-Dist: cos-python-sdk-v5
Requires-Dist: qiniu
Requires-Dist: upyun
Requires-Dist: Pillow
Requires-Dist: tinify
Dynamic: license-file
